SeleniumLogin/__init__.py
SeleniumLogin/login.py
SeleniumLogin/core/__init__.py
SeleniumLogin/core/bilibili.py
SeleniumLogin/core/taobao.py
SeleniumLogin/utils/__init__.py
SeleniumLogin/utils/cookies.py
SeleniumLogin/utils/tracks.py
SeleniumLogin-0.0.4.dist-info/LICENSE
SeleniumLogin-0.0.4.dist-info/METADATA
SeleniumLogin-0.0.4.dist-info/WHEEL
SeleniumLogin-0.0.4.dist-info/top_level.txt
SeleniumLogin-0.0.4.dist-info/zip-safe
SeleniumLogin-0.0.4.dist-info/RECORD
