Metadata-Version: 2.1
Name: SeleniumLogin
Version: 0.0.4
Summary: Login some website using selenium.
Home-page: https://github.com/CharlesPikachu/SeleniumLogin
Author: Charles
Author-email: charlesjzc@qq.com
License: MIT
Platform: UNKNOWN
Classifier: License :: OSI Approved :: MIT License
Classifier: Programming Language :: Python :: 3
Classifier: Intended Audience :: Developers
Classifier: Operating System :: OS Independent
